Metadata-Version: 2.1
Name: vidsz
Version: 0.2.0
Summary: Common Wrapper/Interface around various video reading/writing tools
Home-page: https://github.com/BlueMirrors/vidsz
Author: BlueMirrors
Author-email: contact.bluemirrors@gmail.com
License: Apache Software License v2.0
Platform: UNKNOWN
Classifier: License :: OSI Approved :: Apache Software License
Classifier: Programming Language :: Python :: 3
Classifier: Programming Language :: Python :: 3.6
Classifier: Programming Language :: Python :: 3.7
Classifier: Programming Language :: Python :: 3.8
Classifier: Programming Language :: Python :: 3.9
Requires-Dist: opencv-python
